MANIFEST.in
README.rst
__init__.py
__main__.py
setup.cfg
v.py
bin/activate_this.py
colorama/__init__.py
colorama/ansi.py
colorama/ansitowin32.py
colorama/initialise.py
colorama/win32.py
colorama/winterm.py
e/__init__.py
k/Mac.py
k/__init__.py
k/password_input.py
k/test.py
k/useless.py
p/__init__.py
p/beginnings.py
p/pdsys.py
p/qt.py
p/y.py
p/yh.py
p/yz.py
pip_check/__init__.py
pip_check/get_pip.py
pip_check/pip_.py
requires_LICENSE/LICENCE(tqdm).txt
requires_LICENSE/LICENSE(colorama).txt
requires_LICENSE/LICENSE(netfaces).txt
sycc.egg-info/PKG-INFO
sycc.egg-info/SOURCES.txt
sycc.egg-info/dependency_links.txt
sycc.egg-info/entry_points.txt
sycc.egg-info/requires.txt
sycc.egg-info/top_level.txt
sycc.egg-info/zip-safe
sycc_/__init__.py
sycc_/_virtualenv.py
sycc_/core.py
sycc_/sycc.py
sycc_/v.py
sycc_/_distutils_hack/__init__.py
sycc_/_distutils_hack/override.py
sycc_/pip/__init__.py
sycc_/pip/__main__.py
sycc_/pip/_internal/__init__.py
sycc_/pip/_internal/build_env.py
sycc_/pip/_internal/cache.py
sycc_/pip/_internal/configuration.py
sycc_/pip/_internal/exceptions.py
sycc_/pip/_internal/main.py
sycc_/pip/_internal/pyproject.py
sycc_/pip/_internal/self_outdated_check.py
sycc_/pip/_internal/wheel_builder.py
sycc_/pip/_internal/cli/__init__.py
sycc_/pip/_internal/cli/autocompletion.py
sycc_/pip/_internal/cli/base_command.py
sycc_/pip/_internal/cli/cmdoptions.py
sycc_/pip/_internal/cli/command_context.py
sycc_/pip/_internal/cli/main.py
sycc_/pip/_internal/cli/main_parser.py
sycc_/pip/_internal/cli/parser.py
sycc_/pip/_internal/cli/progress_bars.py
sycc_/pip/_internal/cli/req_command.py
sycc_/pip/_internal/cli/spinners.py
sycc_/pip/_internal/cli/status_codes.py
sycc_/pip/_internal/commands/__init__.py
sycc_/pip/_internal/commands/cache.py
sycc_/pip/_internal/commands/check.py
sycc_/pip/_internal/commands/completion.py
sycc_/pip/_internal/commands/configuration.py
sycc_/pip/_internal/commands/debug.py
sycc_/pip/_internal/commands/download.py
sycc_/pip/_internal/commands/freeze.py
sycc_/pip/_internal/commands/hash.py
sycc_/pip/_internal/commands/help.py
sycc_/pip/_internal/commands/index.py
sycc_/pip/_internal/commands/install.py
sycc-0.8.5.dist-info/LICENSE
sycc-0.8.5.dist-info/METADATA
sycc-0.8.5.dist-info/WHEEL
sycc-0.8.5.dist-info/entry_points.txt
sycc-0.8.5.dist-info/top_level.txt
sycc-0.8.5.dist-info/zip-safe
sycc-0.8.5.dist-info/RECORD
