Metadata-Version: 2.1
Name: sycc
Version: 0.8.5
Summary: 虹源三式(一个有技术含量的四圆计算器)
Home-page: https://project.sycc1.tk
Author: 神秘的·
Author-email: lwb@sycc1.tk
License: SYCC license
Project-URL: github, https://github.com/py-lwb/sycc
Project-URL: pypi, https://pypi.org/project/sycc/
Project-URL: home, https://project.sycc1.tk
Keywords: sycc,3y,a_3y,Circle,圆,圆柱,圆环,py,Chinese,ycc,python,windows,linux,3,y,yh,yz,qt,4,4y,计算器,Calculator,edu
Platform: UNKNOWN
Classifier: Natural Language :: Chinese (Simplified)
Classifier: Development Status :: 6 - Mature
Classifier: Operating System :: Microsoft :: Windows
Classifier: Operating System :: POSIX :: Linux
Classifier: Operating System :: Android
Classifier: Topic :: Scientific/Engineering :: Mathematics
Classifier: Topic :: Terminals
Classifier: Topic :: System :: Shells
Classifier: Programming Language :: Python :: 3
Classifier: Programming Language :: Python :: 3 :: Only
Classifier: Programming Language :: Python :: 3.6
Classifier: Programming Language :: Python :: 3.7
Classifier: Programming Language :: Python :: 3.8
Classifier: Programming Language :: Python :: 3.9
Classifier: Intended Audience :: Developers
Requires-Python: >=3.6
Requires-Dist: netifaces (>=0.11.0)
Requires-Dist: pip
Requires-Dist: sycc (>=0.7.0)
